stamina/__init__.py
stamina/src/__init__.py
stamina/src/main.py
stamina/src/stamina.py
stamina/src/core/__init__.py
stamina/src/core/config.py
stamina/src/core/constants.py
stamina/src/core/entity.py
stamina/src/core/enums.py
stamina/src/core/logging.py
stamina/src/core/project.py
stamina/src/core/publish.py
stamina/src/core/pull.py
stamina/src/core/save.py
stamina/src/core/scene.py
stamina/src/core/socketUtils.py
stamina/src/core/step.py
stamina/src/core/update.py
stamina/src/core/utils.py
stamina/src/desktop/__init__.py
stamina/src/desktop/desktop.py
stamina/src/plugins/__init__.py
stamina/src/plugins/houdini.py
stamina/src/plugins/maya.py
stamina/src/ui/__init__.py
stamina/src/ui/staminaWindow.py
stamina/test/__init__.py
stamina/test/test.py
stamina_pipeline-0.0.31.dist-info/LICENSE.txt
stamina_pipeline-0.0.31.dist-info/METADATA
stamina_pipeline-0.0.31.dist-info/WHEEL
stamina_pipeline-0.0.31.dist-info/top_level.txt
stamina_pipeline-0.0.31.dist-info/RECORD
